django_htmx_modal_redirect/__init__.py
django_htmx_modal_redirect/middleware.py
django_htmx_modal_redirect-0.1.1.dist-info/METADATA
django_htmx_modal_redirect-0.1.1.dist-info/WHEEL
django_htmx_modal_redirect-0.1.1.dist-info/RECORD
