Metadata-Version: 2.1
Name: django-htmx-modal-redirect
Version: 0.1.1
Summary: `django-htmx-modal-redirect` is a Django middleware that intercepts direct URL requests intended for HTMX modals, rendering a fallback view with injected HTMX code to automatically open the modal, such as opening a user profile modal when a user visits `/user/123/` directly, briefly showing the home page before the modal opens.
License: MIT
Author: Christian Tanul
Author-email: contact@tanulchristian.dev
Requires-Python: >=3.12,<4.0
Classifier: License :: OSI Approved :: MIT License
Classifier: Programming Language :: Python :: 3
Classifier: Programming Language :: Python :: 3.12
Requires-Dist: django (>=5.0.7,<6.0.0)
